dclxviclan/__init__.py
dclxviclan/dclxviclan.py
dclxviclan/dclxviclans.py
dclxviclan/module_dclxviclans.py
dclxviclan-31.31.1332.dist-info/METADATA
dclxviclan-31.31.1332.dist-info/WHEEL
dclxviclan-31.31.1332.dist-info/top_level.txt
dclxviclan-31.31.1332.dist-info/RECORD
